COPYING.txt
MANIFEST.in
README.rst
requirements.txt
setup.py
TMgr.egg-info/PKG-INFO
TMgr.egg-info/SOURCES.txt
TMgr.egg-info/dependency_links.txt
TMgr.egg-info/entry_points.txt
TMgr.egg-info/requires.txt
TMgr.egg-info/top_level.txt
tmgr/__init__.py
tmgr/__main__.py
tmgr/cli.py
tmgr/contexts.py
tmgr/main.py
tmgr/renderer.py
tmgr/utils.py