Metadata-Version: 1.1
Name: TMgr
Version: 0.2.2
Summary: A template manager for the command line.
Home-page: https://github.com/NoviceLive/tmgr
Author: Gu Zhengxiong
Author-email: rectigu@gmail.com
License: GPL-3
Keywords: Template,Command line
Platform: UNKNOWN
Classifier: Development Status :: 4 - Beta
Classifier: Environment :: Console
Classifier: License :: OSI Approved :: GNU General Public License v3 or later (GPLv3+)
Classifier: Operating System :: OS Independent
Classifier: Programming Language :: Python :: 2.7
Classifier: Programming Language :: Python :: 3
